pyuserside/__init__.py
pyuserside/api.py
pyuserside/exceptions.py
pyuserside/parser.py
pyuserside/asyncio/__init__.py
pyuserside/asyncio/api.py
pyuserside-0.2.1.dist-info/LICENSE
pyuserside-0.2.1.dist-info/METADATA
pyuserside-0.2.1.dist-info/WHEEL
pyuserside-0.2.1.dist-info/top_level.txt
pyuserside-0.2.1.dist-info/RECORD
